txz_aircon_bailian_mcp_server/__init__.py
txz_aircon_bailian_mcp_server/tool_server.py
txz_aircon_bailian_mcp_server-0.1.7.dist-info/WHEEL
txz_aircon_bailian_mcp_server-0.1.7.dist-info/entry_points.txt
txz_aircon_bailian_mcp_server-0.1.7.dist-info/METADATA
txz_aircon_bailian_mcp_server-0.1.7.dist-info/RECORD
