Metadata-Version: 2.3
Name: txz_aircon_bailian-mcp-server
Version: 0.1.7
Summary: Add your description here
Author: Beili
Author-email: Beili <978228339@qq.com>
Requires-Dist: bs4>=0.0.2
Requires-Dist: dashscope>=1.25.5
Requires-Dist: dotenv>=0.9.9
Requires-Dist: httpx>=0.28.1
Requires-Dist: mcp[cli]>=1.24.0
Requires-Python: >=3.12
